logicpwn/__init__.py
logicpwn/core/__init__.py
logicpwn/core/access/__init__.py
logicpwn/core/access/auth_integration.py
logicpwn/core/access/baseline.py
logicpwn/core/access/core_logic.py
logicpwn/core/access/detector.py
logicpwn/core/access/id_generation.py
logicpwn/core/access/models.py
logicpwn/core/access/privilege_escalation.py
logicpwn/core/access/protocol_support.py
logicpwn/core/access/result_streaming.py
logicpwn/core/access/tenant_isolation.py
logicpwn/core/access/utils.py
logicpwn/core/access/validation.py
logicpwn/core/auth/__init__.py
logicpwn/core/auth/auth_constants.py
logicpwn/core/auth/auth_models.py
logicpwn/core/auth/auth_session.py
logicpwn/core/auth/auth_utils.py
logicpwn/core/auth/http_client.py
logicpwn/core/auth/idp_integration.py
logicpwn/core/auth/jwt_handler.py
logicpwn/core/cache/__init__.py
logicpwn/core/cache/cache.py
logicpwn/core/cache/cache_manager.py
logicpwn/core/cache/cache_utils.py
logicpwn/core/cache/config_cache.py
logicpwn/core/cache/response_cache.py
logicpwn/core/cache/session_cache.py
logicpwn/core/config/__init__.py
logicpwn/core/config/config.py
logicpwn/core/config/config_env.py
logicpwn/core/config/config_models.py
logicpwn/core/config/config_utils.py
logicpwn/core/config/config_validator.py
logicpwn/core/exploit_engine/__init__.py
logicpwn/core/exploit_engine/exploit_engine.py
logicpwn/core/exploit_engine/exploit_logger.py
logicpwn/core/exploit_engine/models.py
logicpwn/core/exploit_engine/payload_generator.py
logicpwn/core/exploit_engine/security_validator.py
logicpwn/core/exploit_engine/validation_engine.py
logicpwn/core/integration_utils.py
logicpwn/core/logging/__init__.py
logicpwn/core/logging/log_functions.py
logicpwn/core/logging/logger.py
logicpwn/core/logging/redactor.py
logicpwn/core/middleware/__init__.py
logicpwn/core/middleware/circuit_breaker.py
logicpwn/core/middleware/middleware.py
logicpwn/core/performance/__init__.py
logicpwn/core/performance/memory_profiler.py
logicpwn-0.3.0.dist-info/METADATA
logicpwn-0.3.0.dist-info/WHEEL
logicpwn-0.3.0.dist-info/RECORD
