Metadata-Version: 2.3
Name: logicpwn
Version: 0.3.0
Summary: LogicPwn represents a paradigm shift from traditional security testing toward intelligent, business-aware security automation. Its unique focus on business logic vulnerabilities, combined with enterprise-grade performance and comprehensive documentation, positions it as a leader in the next generation of security testing tools.
Author: Jash Naik
Author-email: jashnaik2004@gmail.com
Requires-Python: >=3.9,<4.0
Classifier: Programming Language :: Python :: 3
Classifier: Programming Language :: Python :: 3.9
Classifier: Programming Language :: Python :: 3.10
Classifier: Programming Language :: Python :: 3.11
Classifier: Programming Language :: Python :: 3.12
Classifier: Programming Language :: Python :: 3.13
Provides-Extra: access
Provides-Extra: auth
Provides-Extra: exploit
Provides-Extra: performance
Provides-Extra: reliability
Provides-Extra: reporter
Provides-Extra: runner
Provides-Extra: stress
Provides-Extra: validator
Requires-Dist: aiohttp (>=3.9.0,<4.0.0) ; extra == "runner" or extra == "stress"
Requires-Dist: cryptography (>=42.0.0,<43.0.0) ; extra == "auth"
Requires-Dist: httpx (>=0.28.1,<0.29.0)
Requires-Dist: jsonpath-ng (>=1.7.0,<2.0.0) ; extra == "validator"
Requires-Dist: loguru (>=0.7.2,<0.8.0) ; extra == "auth" or extra == "runner" or extra == "access" or extra == "validator" or extra == "reporter" or extra == "performance" or extra == "stress" or extra == "exploit" or extra == "reliability"
Requires-Dist: psutil (>=5.9.0,<6.0.0) ; extra == "performance" or extra == "stress"
Requires-Dist: pydantic (>=2.5.0,<3.0.0) ; extra == "auth" or extra == "runner" or extra == "access" or extra == "validator" or extra == "reporter" or extra == "performance" or extra == "stress" or extra == "exploit" or extra == "reliability"
Requires-Dist: pyjwt (>=2.10.1,<3.0.0)
Requires-Dist: pytest-asyncio (<1.0) ; extra == "runner" or extra == "stress"
Requires-Dist: pyyaml (>=6.0.2,<7.0.0) ; extra == "reporter" or extra == "exploit"
Requires-Dist: qrcode (>=8.2,<9.0) ; extra == "auth"
Requires-Dist: regex (>=2023.12.25,<2024.0.0) ; extra == "validator"
Requires-Dist: requests (>=2.31.0,<3.0.0) ; extra == "auth" or extra == "runner" or extra == "access" or extra == "validator" or extra == "reporter" or extra == "performance" or extra == "stress" or extra == "exploit" or extra == "reliability"
Requires-Dist: sphinx (>=7.4.7,<8.0.0)
Requires-Dist: sphinx-rtd-theme (>=3.0.2,<4.0.0)
Requires-Dist: tenacity (>=9.1.2,<10.0.0) ; extra == "reliability"
Requires-Dist: websockets (>=15.0.1,<16.0.0)
